Metadata-Version: 2.2
Name: ocsmesh
Version: 1.6.4
Summary: Package to generate computational unstructured meshes from planetary modeling.
Author-email: Jaime R Calzada <jreniel@gmail.com>, Soroosh Mani <soroosh.mani@noaa.gov>
Maintainer-email: Soroosh Mani <soroosh.mani@noaa.gov>
License: Creative Commons Legal Code
Project-URL: Documentation, https://noaa-ocs-modeling.github.io/OCSMesh/
Project-URL: Source, https://github.com/noaa-ocs-modeling/OCSMesh/
Requires-Python: >=3.9
License-File: LICENSE
Requires-Dist: colored-traceback<=0.3.0
Requires-Dist: fiona
Requires-Dist: geopandas>=1.0.0
Requires-Dist: jigsawpy
Requires-Dist: matplotlib>=3.8
Requires-Dist: netCDF4
Requires-Dist: numba
Requires-Dist: numpy>=1.21
Requires-Dist: pyarrow
Requires-Dist: rtree
Requires-Dist: pyproj>=3.0
Requires-Dist: rasterio
Requires-Dist: scipy
Requires-Dist: shapely
Requires-Dist: triangle
Requires-Dist: typing_extensions
Requires-Dist: utm
Provides-Extra: testing
Requires-Dist: pylint>=2.14; extra == "testing"
Provides-Extra: documentation
Requires-Dist: sphinx<7.0.0; extra == "documentation"
Requires-Dist: sphinx-rtd-theme; extra == "documentation"
Requires-Dist: sphinx-argparse; extra == "documentation"
Requires-Dist: mistune==0.8.4; extra == "documentation"
Requires-Dist: m2r2; extra == "documentation"
Requires-Dist: numpydoc; extra == "documentation"
